LICENSE.txt
README.md
setup.py
ezzdl/__init__.py
ezzdl/download.py
ezzdl.egg-info/PKG-INFO
ezzdl.egg-info/SOURCES.txt
ezzdl.egg-info/dependency_links.txt
ezzdl.egg-info/requires.txt
ezzdl.egg-info/top_level.txt