Metadata-Version: 2.1
Name: ezzdl
Version: 3.0.0
Summary: Cool download manager based on rich and its sample code
Home-page: https://github.com/BarsTiger/ezzdl
Author: BarsTiger
License: MIT
Keywords: threading,thread,decorator,crossplatform
Platform: UNKNOWN
License-File: LICENSE.txt
